{
	"info": {
		"_postman_id": "c125f0ab-fb70-42b8-b513-6d96234a2199",
		"name": "ParcialDiseño",
		"schema": "https://schema.getpostman.com/json/collection/v2.1.0/collection.json",
		"_exporter_id": "34024076"
	},
	"item": [
		{
			"name": "dna",
			"request": {
				"method": "POST",
				"header": [],
				"body": {
					"mode": "raw",
					"raw": "{\"dna\":[\"ATGCGA\",\"CAGTGC\",\"TTATGT\",\"AGAAGG\",\"CCCCTA\",\"TCACTG\"]}",
					"options": {
						"raw": {
							"language": "json"
						}
					}
				},
				"url": {
					"raw": "http://127.0.0.1:5000/mutant/",
					"protocol": "http",
					"host": [
						"127",
						"0",
						"0",
						"1"
					],
					"port": "5000",
					"path": [
						"mutant",
						""
					]
				}
			},
			"response": []
		},
		{
			"name": "dna  no mutante",
			"request": {
				"method": "POST",
				"header": [],
				"body": {
					"mode": "raw",
					"raw": "{\"dna\":[\"ATGCGA\",\"CAGTGC\",\"TTATGT\",\"AGAAGG\",\"CCCCTA\",\"TCACTG\"]}",
					"options": {
						"raw": {
							"language": "json"
						}
					}
				},
				"url": {
					"raw": "http://127.0.0.1:5000/mutant/",
					"protocol": "http",
					"host": [
						"127",
						"0",
						"0",
						"1"
					],
					"port": "5000",
					"path": [
						"mutant",
						""
					]
				}
			},
			"response": []
		},
		{
			"name": "estados de dna",
			"request": {
				"method": "GET",
				"header": [],
				"url": {
					"raw": "http://127.0.0.1:5000/stats",
					"protocol": "http",
					"host": [
						"127",
						"0",
						"0",
						"1"
					],
					"port": "5000",
					"path": [
						"stats"
					]
				}
			},
			"response": []
		}
	]
}